{
  "AdsManager": {
    "AdNetwork": "applovin",
    "AdmobBanner": "",
    "AdmobInterstitial": "",
    "AdmobNative": "",

    "ApplovinBanner": "c53b72466bfa6a6e",

    "ApplovinInterstitial": "8ad152cb6c3d89f4",

    "ApplovinNative": "4099e91e706974a8",

    "UnityGameID": "4848007",
    "UnityBanner": "Banner_Android",
    "UnityInterstitial": "Interstitial_Android",

    "imggame1": "https://cdnb.artstation.com/p/assets/images/images/062/578/077/large/paula-valiente-amanda-the-adventurer-redi.jpg",
    "urlgame1": "https://play.google.com/store/apps/details?id=com.HdWallpaper.PhoenixWallpaper",

    "imggame2": "https://amandatheadventurergame.io//data/image/game/amanda-the-adventurer-feature-image.jpg",
    "urlgame2": "https://play.google.com/store/apps/details?id=com.Hdwallpaper.aesthetic.aesthetic_wallpaper",

    "imggame3": "https://amandatheadventurergame.io//data/image/game/amanda-the-adventurer-feature-image.jpg",
    "urlgame3": "https://play.google.com/store/apps/details?id=com.Hdwallpaper.aesthetic.aesthetic_wallpaper",

    "RatingActive": true,
    "ads_mode": true
  }
}
